hue_color_converter/__init__.py
hue_color_converter/converter.py
hue_color_converter/gamuts.py
hue_color_converter-0.2.4.dist-info/LICENSE.txt
hue_color_converter-0.2.4.dist-info/METADATA
hue_color_converter-0.2.4.dist-info/WHEEL
hue_color_converter-0.2.4.dist-info/RECORD
