Metadata-Version: 2.1
Name: hue-color-converter
Version: 0.2.4
Summary: color converter for philips hue
License: MIT
Author: Zachary Juang
Author-email: zachary822@me.com
Requires-Python: >=3.10,<3.12
Classifier: License :: OSI Approved :: MIT License
Classifier: Programming Language :: Python :: 3
Classifier: Programming Language :: Python :: 3.10
Classifier: Programming Language :: Python :: 3.11
Requires-Dist: Shapely (>=2.0.1,<3.0.0)
Requires-Dist: numpy (>=1.23.2,<2.0.0)
Project-URL: repository, https://github.com/zachary822/hue_color_converter
